{
    "anvil_cost":  4,
    "description":  {
                        "translate":  "enchantment.scguns.lightweight"
                    },
    "exclusive_set":  "#scguns:exclusive_set/weapon",
    "max_cost":  {
                     "base":  35,
                     "per_level_above_first":  0
                 },
    "max_level":  2,
    "min_cost":  {
                     "base":  15,
                     "per_level_above_first":  0
                 },
    "slots":  [
                  "mainhand"
              ],
    "supported_items":  "#scguns:enchantable/gun",
    "weight":  2
}
