{
	"format_version": "1.21.6",
	"credit": "Made with Blockbench",
	"texture_size": [64, 64],
	"textures": {
		"1": "scguns:item/sterilizer"
	},
	"elements": [
		{
			"name": "sights",
			"from": [7.78716, 6.9779, 13.06078],
			"to": [7.95284, 7.0779, 13.15878],
			"rotation": {"angle": 45, "axis": "z", "origin": [7.87, 7.1779, 13.10978]},
			"faces": {
				"north": {"uv": [9.25, 6.75, 9.375, 6.875], "texture": "#1"},
				"east": {"uv": [7, 9.25, 7.125, 9.375], "texture": "#1"},
				"south": {"uv": [9.25, 7, 9.375, 7.125], "texture": "#1"},
				"west": {"uv": [7.25, 9.25, 7.375, 9.375], "texture": "#1"},
				"up": {"uv": [9.375, 7.375, 9.25, 7.25], "texture": "#1"},
				"down": {"uv": [7.625, 9.25, 7.5, 9.375], "texture": "#1"}
			}
		},
		{
			"name": "sights",
			"from": [7.77466, 6.9779, 13.05978],
			"to": [7.96534, 7.0779, 13.15978],
			"rotation": {"angle": 0, "axis": "y", "origin": [7.86053, 8.8279, 10.13478]},
			"faces": {
				"north": {"uv": [9.25, 7.5, 9.375, 7.625], "texture": "#1"},
				"east": {"uv": [7.75, 9.25, 7.875, 9.375], "texture": "#1"},
				"south": {"uv": [9.25, 7.75, 9.375, 7.875], "texture": "#1"},
				"west": {"uv": [8, 9.25, 8.125, 9.375], "texture": "#1"},
				"up": {"uv": [9.375, 8.125, 9.25, 8], "texture": "#1"},
				"down": {"uv": [8.375, 9.25, 8.25, 9.375], "texture": "#1"}
			}
		},
		{
			"name": "sights",
			"from": [7.78716, 7.2529, 13.06078],
			"to": [7.92784, 7.3529, 13.15878],
			"rotation": {"angle": 45, "axis": "z", "origin": [7.87, 7.1529, 13.10978]},
			"faces": {
				"north": {"uv": [9.25, 8.25, 9.375, 8.375], "texture": "#1"},
				"east": {"uv": [8.5, 9.25, 8.625, 9.375], "texture": "#1"},
				"south": {"uv": [9.25, 8.5, 9.375, 8.625], "texture": "#1"},
				"west": {"uv": [8.75, 9.25, 8.875, 9.375], "texture": "#1"},
				"up": {"uv": [9.375, 8.875, 9.25, 8.75], "texture": "#1"},
				"down": {"uv": [9.125, 9.25, 9, 9.375], "texture": "#1"}
			}
		},
		{
			"name": "sights",
			"from": [7.67, 7.09506, 13.06078],
			"to": [7.77, 7.26074, 13.15878],
			"rotation": {"angle": 45, "axis": "z", "origin": [7.87, 7.1779, 13.10978]},
			"faces": {
				"north": {"uv": [9.25, 9, 9.375, 9.125], "texture": "#1"},
				"east": {"uv": [9.25, 9.25, 9.375, 9.375], "texture": "#1"},
				"south": {"uv": [0, 9.5, 0.125, 9.625], "texture": "#1"},
				"west": {"uv": [9.5, 0, 9.625, 0.125], "texture": "#1"},
				"up": {"uv": [0.375, 9.625, 0.25, 9.5], "texture": "#1"},
				"down": {"uv": [9.625, 0.25, 9.5, 0.375], "texture": "#1"}
			}
		},
		{
			"name": "sights",
			"from": [7.67, 6.97006, 13.05978],
			"to": [7.77, 7.23574, 13.15978],
			"rotation": {"angle": 0, "axis": "y", "origin": [7.86053, 8.8279, 10.13478]},
			"faces": {
				"north": {"uv": [0.5, 9.5, 0.625, 9.625], "texture": "#1"},
				"east": {"uv": [9.5, 0.5, 9.625, 0.625], "texture": "#1"},
				"south": {"uv": [0.75, 9.5, 0.875, 9.625], "texture": "#1"},
				"west": {"uv": [9.5, 0.75, 9.625, 0.875], "texture": "#1"},
				"up": {"uv": [1.125, 9.625, 1, 9.5], "texture": "#1"},
				"down": {"uv": [9.625, 1, 9.5, 1.125], "texture": "#1"}
			}
		},
		{
			"name": "sights",
			"from": [7.97, 7.07006, 13.06078],
			"to": [8.07, 7.21074, 13.15878],
			"rotation": {"angle": 45, "axis": "z", "origin": [7.87, 7.1529, 13.10978]},
			"faces": {
				"north": {"uv": [1.25, 9.5, 1.375, 9.625], "texture": "#1"},
				"east": {"uv": [9.5, 1.25, 9.625, 1.375], "texture": "#1"},
				"south": {"uv": [1.5, 9.5, 1.625, 9.625], "texture": "#1"},
				"west": {"uv": [9.5, 1.5, 9.625, 1.625], "texture": "#1"},
				"up": {"uv": [1.875, 9.625, 1.75, 9.5], "texture": "#1"},
				"down": {"uv": [9.625, 1.75, 9.5, 1.875], "texture": "#1"}
			}
		},
		{
			"name": "sights",
			"from": [7.97, 6.97006, 13.05978],
			"to": [8.07, 7.23574, 13.15978],
			"rotation": {"angle": 0, "axis": "y", "origin": [7.86053, 8.8279, 10.13478]},
			"faces": {
				"north": {"uv": [2, 9.5, 2.125, 9.625], "texture": "#1"},
				"east": {"uv": [9.5, 2, 9.625, 2.125], "texture": "#1"},
				"south": {"uv": [2.25, 9.5, 2.375, 9.625], "texture": "#1"},
				"west": {"uv": [9.5, 2.25, 9.625, 2.375], "texture": "#1"},
				"up": {"uv": [2.625, 9.625, 2.5, 9.5], "texture": "#1"},
				"down": {"uv": [9.625, 2.5, 9.5, 2.625], "texture": "#1"}
			}
		},
		{
			"name": "sights",
			"from": [7.5325, 6.92557, 12.93711],
			"to": [8.2075, 6.97557, 13.31211],
			"rotation": {"angle": 0, "axis": "y", "origin": [7.86053, 8.8279, 10.13478]},
			"faces": {
				"north": {"uv": [2.75, 9.5, 2.875, 9.625], "texture": "#1"},
				"east": {"uv": [9.5, 2.75, 9.625, 2.875], "texture": "#1"},
				"south": {"uv": [3, 9.5, 3.125, 9.625], "texture": "#1"},
				"west": {"uv": [9.5, 3, 9.625, 3.125], "texture": "#1"},
				"up": {"uv": [3.375, 9.625, 3.25, 9.5], "texture": "#1"},
				"down": {"uv": [9.625, 3.25, 9.5, 3.375], "texture": "#1"}
			}
		}
	],
	"display": {
		"thirdperson_righthand": {
			"translation": [0, 5.75, -5],
			"scale": [1.2, 1.2, 1.2]
		},
		"thirdperson_lefthand": {
			"translation": [0, 5.75, -5],
			"scale": [1.2, 1.2, 1.2]
		},
		"firstperson_righthand": {
			"translation": [-5.25, 8.75, 0.75]
		},
		"firstperson_lefthand": {
			"translation": [-5.25, 8.75, 0.75]
		},
		"ground": {
			"translation": [0, 9.5, 4.75],
			"scale": [1.2, 1.2, 1.2]
		},
		"gui": {
			"rotation": [74.02, -53.34, 70.48],
			"translation": [-3.25, 2.75, 0],
			"scale": [0.9, 0.9, 0.9]
		},
		"fixed": {
			"rotation": [90, 55, -90],
			"translation": [6.75, 3.5, 0],
			"scale": [1.3, 1.3, 1.3]
		}
	},
	"groups": [
		{
			"name": "sights",
			"origin": [0, -1.10125, 12.2125],
			"color": 4,
			"children": [0, 1, 2, 3, 4, 5, 6, 7]
		}
	]
}